surfdataverse/__init__.py
surfdataverse/container.py
surfdataverse/core.py
surfdataverse/exceptions.py
surfdataverse-4.0.2.dist-info/WHEEL
surfdataverse-4.0.2.dist-info/METADATA
surfdataverse-4.0.2.dist-info/RECORD
