Metadata-Version: 2.3
Name: surfdataverse
Version: 4.0.2
Summary: A Python package for ionysis Microsoft Dataverse integration
Keywords: dataverse,microsoft,crm,api
Author: ionysis
Author-email: ionysis <friedemann.heinz@ionysis.com>
License: MIT
Classifier: Development Status :: 3 - Alpha
Classifier: Intended Audience :: Developers
Classifier: License :: OSI Approved :: MIT License
Classifier: Programming Language :: Python :: 3
Classifier: Programming Language :: Python :: 3.8
Classifier: Programming Language :: Python :: 3.9
Classifier: Programming Language :: Python :: 3.10
Classifier: Programming Language :: Python :: 3.11
Requires-Dist: dependency-injector>=4.42.0
Requires-Dist: msal>=1.33.0
Requires-Dist: numpy>=2.3.3
Requires-Dist: pandas>=2.3.2
Requires-Dist: polars>=1.34.0
Requires-Dist: requests>=2.32.5
Requires-Python: >=3.11
Project-URL: Bug Tracker, https://github.com/FriedemannHeinz/SurfDataverse/issues
Project-URL: Documentation, https://github.com/FriedemannHeinz/SurfDataverse#readme
Project-URL: Homepage, https://github.com/FriedemannHeinz/SurfDataverse
Project-URL: Repository, https://github.com/FriedemannHeinz/SurfDataverse.git
